purecpp_extract_dev/__init__.py
purecpp_extract_dev/purecpp_extract_dev.cpython-311-x86_64-linux-gnu.so
purecpp_extract_dev-0.0.400.dist-info/METADATA
purecpp_extract_dev-0.0.400.dist-info/WHEEL
purecpp_extract_dev-0.0.400.dist-info/top_level.txt
purecpp_extract_dev-0.0.400.dist-info/RECORD
